Metadata-Version: 1.0
Name: vtfunc
Version: 0.4.0
Summary: Tabular user-defined functions for SQLite3.
Home-page: https://github.com/coleifer/sqlite-vtfunc
Author: Charles Leifer
Author-email: UNKNOWN
License: UNKNOWN
Platform: UNKNOWN
